aviary/envs/litqa/__init__.py
aviary/envs/litqa/env.py
aviary/envs/litqa/py.typed
aviary/envs/litqa/task.py
aviary/envs/litqa/version.py
aviary_litqa-0.29.0.dist-info/METADATA
aviary_litqa-0.29.0.dist-info/WHEEL
aviary_litqa-0.29.0.dist-info/top_level.txt
aviary_litqa-0.29.0.dist-info/RECORD
