Metadata-Version: 2.4
Name: aviary.litqa
Version: 0.29.0
Summary: LitQA environment implemented with aviary
Author-email: FutureHouse technical staff <hello@futurehouse.org>
Classifier: Intended Audience :: Developers
Classifier: License :: OSI Approved :: Apache Software License
Classifier: Operating System :: OS Independent
Classifier: Programming Language :: Python :: 3 :: Only
Classifier: Programming Language :: Python :: 3.11
Classifier: Programming Language :: Python :: 3.12
Classifier: Programming Language :: Python :: 3.13
Classifier: Programming Language :: Python :: 3.14
Classifier: Programming Language :: Python
Classifier: Topic :: Scientific/Engineering :: Artificial Intelligence
Requires-Python: >=3.11
Requires-Dist: fhaviary>=0.14
Requires-Dist: fhlmi
Requires-Dist: ldp>=0.25.2
Requires-Dist: paper-qa>=5.14.0
Requires-Dist: pydantic~=2.0
Requires-Dist: tenacity
Requires-Dist: typing-extensions; python_version <= "3.12"
Provides-Extra: datasets
Requires-Dist: datasets>=2.15; extra == "datasets"
Provides-Extra: dev
Requires-Dist: aviary.litqa[datasets]; extra == "dev"
Requires-Dist: paper-qa>=5.29.1; extra == "dev"
Requires-Dist: tantivy>=0.25.0; python_version >= "3.14" and extra == "dev"
